tq_datasets/__init__.py
tq_datasets/dataset_op_interface/__init__.py
tq_datasets/dataset_op_interface/organize_dataset.py
tq_datasets/dataset_op_interface/traverse_dataset.py
tq_datasets/utils/__init__.py
tq_datasets-0.1.1.dist-info/METADATA
tq_datasets-0.1.1.dist-info/WHEEL
tq_datasets-0.1.1.dist-info/top_level.txt
tq_datasets-0.1.1.dist-info/RECORD
